MANIFEST.in
README.rst
setup.py
django_flexible_content_ckeditor.egg-info/PKG-INFO
django_flexible_content_ckeditor.egg-info/SOURCES.txt
django_flexible_content_ckeditor.egg-info/dependency_links.txt
django_flexible_content_ckeditor.egg-info/requires.txt
django_flexible_content_ckeditor.egg-info/top_level.txt
flexible_ckeditor/__init__.py
flexible_ckeditor/fields.py
flexible_ckeditor/models.py
flexible_ckeditor/tests.py
flexible_ckeditor/widgets.py
flexible_ckeditor/static/flexible_ckeditor/ckeditor/CHANGES.md
flexible_ckeditor/static/flexible_ckeditor/ckeditor/LICENSE.md
flexible_ckeditor/static/flexible_ckeditor/ckeditor/README.md
flexible_ckeditor/static/flexible_ckeditor/ckeditor/build-config.js
flexible_ckeditor/static/flexible_ckeditor/ckeditor/ckeditor.js
flexible_ckeditor/static/flexible_ckeditor/ckeditor/config.js
flexible_ckeditor/static/flexible_ckeditor/ckeditor/contents.css
flexible_ckeditor/static/flexible_ckeditor/ckeditor/styles.js
flexible_ckeditor/static/flexible_ckeditor/ckeditor/lang/af.js
flexible_ckeditor/static/flexible_ckeditor/ckeditor/lang/ar.js
flexible_ckeditor/static/flexible_ckeditor/ckeditor/lang/bg.js
flexible_ckeditor/static/flexible_ckeditor/ckeditor/lang/bn.js
flexible_ckeditor/static/flexible_ckeditor/ckeditor/lang/bs.js
flexible_ckeditor/static/flexible_ckeditor/ckeditor/lang/ca.js
flexible_ckeditor/static/flexible_ckeditor/ckeditor/lang/cs.js
flexible_ckeditor/static/flexible_ckeditor/ckeditor/lang/cy.js
flexible_ckeditor/static/flexible_ckeditor/ckeditor/lang/da.js
flexible_ckeditor/static/flexible_ckeditor/ckeditor/lang/de.js
flexible_ckeditor/static/flexible_ckeditor/ckeditor/lang/el.js
flexible_ckeditor/static/flexible_ckeditor/ckeditor/lang/en-au.js
flexible_ckeditor/static/flexible_ckeditor/ckeditor/lang/en-ca.js
flexible_ckeditor/static/flexible_ckeditor/ckeditor/lang/en-gb.js
flexible_ckeditor/static/flexible_ckeditor/ckeditor/lang/en.js
flexible_ckeditor/static/flexible_ckeditor/ckeditor/lang/eo.js
flexible_ckeditor/static/flexible_ckeditor/ckeditor/lang/es.js
flexible_ckeditor/static/flexible_ckeditor/ckeditor/lang/et.js
flexible_ckeditor/static/flexible_ckeditor/ckeditor/lang/eu.js
flexible_ckeditor/static/flexible_ckeditor/ckeditor/lang/fa.js
