Metadata-Version: 1.0
Name: django-flexible-content-ckeditor
Version: 1.0.0
Summary: Rich text (WYSIWYG) support for django-flexible-content
Home-page: https://github.com/hjkelly/django-flexible-content-ckeditor
Author: Harrison Kelly
Author-email: hjkelly@gmail.com
License: UNKNOWN
Platform: UNKNOWN
